pyrestcountries/__init__.py
pyrestcountries/api.py
pyrestcountries/data.py
pyrestcountries-2024.5.31.dist-info/LICENSE
pyrestcountries-2024.5.31.dist-info/METADATA
pyrestcountries-2024.5.31.dist-info/WHEEL
pyrestcountries-2024.5.31.dist-info/top_level.txt
pyrestcountries-2024.5.31.dist-info/RECORD
