Metadata-Version: 2.1
Name: pyrestcountries
Version: 2024.5.31
Summary: Pythonic wrapper around data served by restcountries API
Home-page: https://github.com/musicmuni/pyrestcountries
Author: Gopala Krishna Koduri
Author-email: gopal@riyazapp.com
Project-URL: Documentation, https://github.com/musicmuni/pyrestcountries
Project-URL: Source, https://github.com/musicmuni/pyrestcountries
Project-URL: Tracker, https://github.com/musicmuni/pyrestcountries/issues
Project-URL: Connect w/ Author, https://linkedin.com/in/gopalkoduri
Project-URL: Riyaz - Learn to sing, https://riyazapp.com
Classifier: Development Status :: 3 - Alpha
Classifier: Intended Audience :: Developers
Classifier: Topic :: Software Development :: Build Tools
Classifier: License :: OSI Approved :: MIT License
Classifier: Programming Language :: Python :: 3
Classifier: Programming Language :: Python :: 3.7
Classifier: Programming Language :: Python :: 3.8
Classifier: Programming Language :: Python :: 3.9
Classifier: Programming Language :: Python :: 3.10
Classifier: Programming Language :: Python :: 3.11
Requires-Python: >=3.7
License-File: LICENSE
Requires-Dist: requests
Requires-Dist: appdirs
Requires-Dist: diskcache
Requires-Dist: thefuzz
